{
    "dataset": "19_landsat",
    "strategy": "LossPredictionLoss",
    "model": "LPL",
    "seed": 0,
    "disable_tqdm": false,
    "use_cuda": true,
    "n_epoch": 50,
    "init_labeled": 450,
    "budget": 2240,
    "budget_ratio": 0.5,
    "batch_size": 224,
    "model_batch_size": 512,
    "input_dim": 36,
    "train_size": 4504,
    "test_size": 1931,
    "all_train_outliers": 933,
    "optimizer": "Adam",
    "process": {
        "round_0": [
            450,
            94,
            224,
            94,
            0.874,
            0.7118,
            "[0.9231,0.5902]"
        ],
        "round_1": [
            674,
            286,
            224,
            192,
            0.9062,
            0.7788,
            "[0.9198,0.6421]"
        ],
        "round_2": [
            898,
            388,
            224,
            102,
            0.9198,
            0.7921,
            "[0.9294,0.6985]"
        ],
        "round_3": [
            1122,
            512,
            224,
            124,
            0.9434,
            0.8462,
            "[0.9382,0.7713]"
        ],
        "round_4": [
            1346,
            592,
            224,
            80,
            0.9454,
            0.8465,
            "[0.9421,0.7672]"
        ],
        "round_5": [
            1570,
            683,
            224,
            91,
            0.9469,
            0.8631,
            "[0.9393,0.6995]"
        ],
        "round_6": [
            1794,
            768,
            224,
            85,
            0.9607,
            0.8907,
            "[0.9448,0.789 ]"
        ],
        "round_7": [
            2018,
            805,
            224,
            37,
            0.963,
            0.899,
            "[0.9523,0.8123]"
        ],
        "round_8": [
            2242,
            821,
            224,
            16,
            0.9649,
            0.8969,
            "[0.9503,0.8114]"
        ],
        "round_9": [
            2466,
            827,
            224,
            6,
            0.966,
            0.9016,
            "[0.9503,0.7919]"
        ],
        "round_10": [
            2690,
            860,
            224,
            33,
            0.9636,
            0.8881,
            "[0.9442,0.7922]"
        ]
    },
    "metrics": {
        "F-aucroc": 0.9636,
        "F_aucpr": 0.8881,
        "F_f1": "[0.9442,0.7922]"
    }
}
