{
    "dataset": "12_fault",
    "strategy": "BadgeSampling",
    "model": "DevNet",
    "seed": 0,
    "disable_tqdm": false,
    "use_cuda": true,
    "n_epoch": 50,
    "init_labeled": 136,
    "budget": 340,
    "budget_ratio": 0.25,
    "batch_size": 34,
    "model_batch_size": 512,
    "input_dim": 27,
    "train_size": 1358,
    "test_size": 583,
    "all_train_outliers": 471,
    "process": {
        "round_0": [
            1358,
            38,
            34,
            38,
            0.6538,
            0.5086,
            "[0.7923,0.1638]"
        ],
        "round_1": [
            1358,
            49,
            34,
            11,
            0.6738,
            0.5486,
            "[0.7966,0.181 ]"
        ],
        "round_2": [
            1358,
            59,
            34,
            10,
            0.6716,
            0.5391,
            "[0.7987,0.1897]"
        ],
        "round_3": [
            1358,
            68,
            34,
            9,
            0.6725,
            0.5281,
            "[0.7987,0.1897]"
        ],
        "round_4": [
            1358,
            74,
            34,
            6,
            0.6701,
            0.5261,
            "[0.7987,0.1897]"
        ],
        "round_5": [
            1358,
            85,
            34,
            11,
            0.6724,
            0.5214,
            "[0.7966,0.181 ]"
        ],
        "round_6": [
            1358,
            94,
            34,
            9,
            0.6591,
            0.4937,
            "[0.7923,0.1638]"
        ],
        "round_7": [
            1358,
            102,
            34,
            8,
            0.6423,
            0.4671,
            "[0.788 ,0.1466]"
        ],
        "round_8": [
            1358,
            113,
            34,
            11,
            0.6382,
            0.4603,
            "[0.7901,0.1552]"
        ],
        "round_9": [
            1358,
            131,
            34,
            18,
            0.6455,
            0.4533,
            "[0.7859,0.1379]"
        ],
        "round_10": [
            1358,
            142,
            34,
            11,
            0.6395,
            0.4499,
            "[0.7859,0.1379]"
        ]
    },
    "metrics": {
        "F-aucroc": 0.6395,
        "F_aucpr": 0.4499,
        "F_f1": "[0.7859,0.1379]"
    }
}
